pipeline/__init__.py
pipeline/_version.py
pipeline/averaging.py
pipeline/boilerplate.py
pipeline/epoching.py
pipeline/group.py
pipeline/io.py
pipeline/participant.py
pipeline/perm.py
pipeline/preprocessing.py
pipeline/report.py
pipeline/ride.py
pipeline/tfr.py
pipeline/datasets/__init__.py
pipeline/datasets/erpcore.py
pipeline/datasets/erpcore_manifest.csv
pipeline/datasets/ucap.py
pipeline/datasets/ucap_manifest.csv
pipeline/datasets/utils.py
hu_neuro_pipeline-0.9.0.dist-info/LICENSE
hu_neuro_pipeline-0.9.0.dist-info/METADATA
hu_neuro_pipeline-0.9.0.dist-info/WHEEL
hu_neuro_pipeline-0.9.0.dist-info/top_level.txt
hu_neuro_pipeline-0.9.0.dist-info/RECORD
