Metadata-Version: 2.1
Name: hu-neuro-pipeline
Version: 0.9.0
Summary: Single trial EEG pipeline at the Abdel Rahman Lab for Neurocognitive Psychology, Humboldt-Universität zu Berlin
Home-page: https://github.com/alexenge/hu-neuro-pipeline
Author: Alexander Enge
Author-email: alexander.enge@hu-berlin.de
Project-URL: Issue trackers, https://github.com/alexenge/hu-neuro-pipeline/issues
Classifier: Programming Language :: Python :: 3.8
Classifier: Programming Language :: Python :: 3.9
Classifier: Programming Language :: Python :: 3.10
Classifier: Programming Language :: Python :: 3.11
Classifier: License :: OSI Approved :: MIT License
Classifier: Operating System :: OS Independent
Requires-Python: >=3.8
License-File: LICENSE
Requires-Dist: chardet
Requires-Dist: eeg-ride
Requires-Dist: joblib
Requires-Dist: matplotlib
Requires-Dist: mne>=0.24.0
Requires-Dist: pandas!=1.4.0
Requires-Dist: pooch>=1.5
Requires-Dist: scikit-learn
